{
  "Japan to fund supplementary budget with $74bn in new debt": {
    "topic_name_ko": "Japan to fund supplementary budget with $74bn in new debt",
    "summary_ko": "",
    "keywords": [],
    "category": "Unclassified",
    "stances": {
      "factual": [
        "345ef042-13c2-4c04-a304-779b3669d215",
        "fa00b03d-231c-40c9-aa9a-dc48192ffd5a",
        "f1b60590-2303-45c8-9f52-de60d5bbb7cc",
        "f67ee249-670a-4312-86d0-798a9a62a425",
        "2fa7c168-c360-4e0c-9b13-b81ae30fa3f9",
        "52d6a351-1b2b-4d79-a905-aff1cf787c87",
        "123ea01a-d32a-4f8e-8b78-e42913c5e8c3"
      ],
      "critical": [],
      "supportive": []
    }
  },
  "Japanese regional airports, Chinese airlines face Taiwan feud fallout": {
    "topic_name_ko": "Japanese regional airports, Chinese airlines face Taiwan feud fallout",
    "summary_ko": "",
    "keywords": [],
    "category": "Unclassified",
    "stances": {
      "factual": [
        "5473af58-a02a-4a86-8d41-3916faebdb0d",
        "e3dd7233-a5b7-4c01-b7e8-756f29eca954",
        "da196d1c-5d45-422b-a232-64fd622273cc"
      ],
      "critical": [],
      "supportive": []
    }
  },
  "The man who changed Foxconn and graphite ambitions in the US": {
    "topic_name_ko": "The man who changed Foxconn and graphite ambitions in the US",
    "summary_ko": "",
    "keywords": [],
    "category": "Unclassified",
    "stances": {
      "factual": [
        "37ffc4fe-8eb7-4a01-9171-886f7f619a05",
        "09da8716-abc3-40e2-99e3-1a42701de353"
      ],
      "critical": [],
      "supportive": []
    }
  },
  "홍콩 고층 아파트 화재, 128명 사망 확인, 약 200명 연락 두절, 홍콩 정부": {
    "topic_name_ko": "홍콩 고층 아파트 화재, 128명 사망 확인, 약 200명 연락 두절, 홍콩 정부",
    "summary_ko": "",
    "keywords": [],
    "category": "Unclassified",
    "stances": {
      "factual": [
        "d7ab344a-3ad8-40dc-b11a-319d5eac251d",
        "9ddc8042-3b02-4bd2-bc06-eb9fedf4b858",
        "195bbf01-ea1b-4ec1-b8c3-0a4c071b4dab",
        "01012771-e483-49c4-8706-cab8d24185ce"
      ],
      "critical": [],
      "supportive": []
    }
  },
  "VinFast leads EV brands in ASEAN as gas-powered car sales stutter": {
    "topic_name_ko": "VinFast leads EV brands in ASEAN as gas-powered car sales stutter",
    "summary_ko": "",
    "keywords": [],
    "category": "Unclassified",
    "stances": {
      "factual": [
        "d959a815-05a2-4369-a9aa-ae04d44d5657",
        "946905d5-94dd-40a3-ba7b-e17a4fd8a774"
      ],
      "critical": [],
      "supportive": []
    }
  },
  "팀랩, 몰입형 예술로 교토 방문객 유치": {
    "topic_name_ko": "팀랩, 몰입형 예술로 교토 방문객 유치",
    "summary_ko": "",
    "keywords": [],
    "category": "Unclassified",
    "stances": {
      "factual": [
        "c0c150ea-6cc1-4622-83d6-fd1defe73d8c",
        "f7925aee-57e8-4f2c-9617-7865be341655"
      ],
      "critical": [],
      "supportive": []
    }
  },
  "아사히, 9월 사이버 공격 피해 규모 마침내 공개; 191만 명 개인정보 유출 가능성": {
    "topic_name_ko": "아사히, 9월 사이버 공격 피해 규모 마침내 공개; 191만 명 개인정보 유출 가능성",
    "summary_ko": "",
    "keywords": [],
    "category": "Unclassified",
    "stances": {
      "factual": [
        "032a04dc-cd0b-4467-b6ab-6e874f14c03c",
        "e4dcc43d-bebf-4154-a520-a317b9d53521",
        "f84c47df-385f-40a8-8429-423a901f3449"
      ],
      "critical": [],
      "supportive": []
    }
  }
}